{
  "parent": "epichunt:root",
  "display": {
    "icon": {
      "item": "minecraft:bow"
    },
    "title": {
      "translate": "advancements.epichunt.sharpshooter.title"
    },
    "description": {
      "translate": "advancements.epichunt.sharpshooter.description"
    },
    "frame": "task",
    "show_toast": true,
    "announce_to_chat": true
  },
  "criteria": {
    "epichunt:duck": {
      "conditions": {
        "entity": [
          {
            "condition": "minecraft:entity_properties",
            "entity": "this",
            "predicate": {
              "type": "epichunt:duck"
            }
          }
        ],
        "killing_blow": {
          "tags": [
            {
              "expected": true,
              "id": "minecraft:is_projectile"
            }
          ]
        }
      },
      "trigger": "minecraft:player_killed_entity"
    },
    "epichunt:pheasant": {
      "conditions": {
        "entity": [
          {
            "condition": "minecraft:entity_properties",
            "entity": "this",
            "predicate": {
              "type": "epichunt:pheasant"
            }
          }
        ],
        "killing_blow": {
          "tags": [
            {
              "expected": true,
              "id": "minecraft:is_projectile"
            }
          ]
        }
      },
      "trigger": "minecraft:player_killed_entity"
    },
    "epichunt:quail": {
      "conditions": {
        "entity": [
          {
            "condition": "minecraft:entity_properties",
            "entity": "this",
            "predicate": {
              "type": "epichunt:quail"
            }
          }
        ],
        "killing_blow": {
          "tags": [
            {
              "expected": true,
              "id": "minecraft:is_projectile"
            }
          ]
        }
      },
      "trigger": "minecraft:player_killed_entity"
    },
    "epichunt:goose": {
      "conditions": {
        "entity": [
          {
            "condition": "minecraft:entity_properties",
            "entity": "this",
            "predicate": {
              "type": "epichunt:goose"
            }
          }
        ],
        "killing_blow": {
          "tags": [
            {
              "expected": true,
              "id": "minecraft:is_projectile"
            }
          ]
        }
      },
      "trigger": "minecraft:player_killed_entity"
    },
    "epichunt:drake": {
      "conditions": {
        "entity": [
          {
            "condition": "minecraft:entity_properties",
            "entity": "this",
            "predicate": {
              "type": "epichunt:drake"
            }
          }
        ],
        "killing_blow": {
          "tags": [
            {
              "expected": true,
              "id": "minecraft:is_projectile"
            }
          ]
        }
      },
      "trigger": "minecraft:player_killed_entity"
    }
  },
  "requirements": [
    [
      "epichunt:duck",
      "epichunt:drake"],
      ["epichunt:pheasant"],
      ["epichunt:goose"],
      ["epichunt:quail"
    ]
  ],
  "sends_telemetry_event": true
}